{
	"info": {
		"_postman_id": "6855498e-ec37-4f78-a2df-4896a1df14df",
		"name": "Search APIs",
		"schema": "https://schema.getpostman.com/json/collection/v2.1.0/collection.json"
	},
	"item": [
		{
			"name": "Search Category",
			"request": {
				"auth": {
					"type": "noauth"
				},
				"method": "GET",
				"header": [],
				"url": {
					"raw": "http://localhost:8080/api/search/category?keyword=IOS&pageNumber=1",
					"protocol": "http",
					"host": [
						"localhost"
					],
					"port": "8080",
					"path": [
						"api",
						"search",
						"category"
					],
					"query": [
						{
							"key": "keyword",
							"value": "IOS"
						},
						{
							"key": "pageNumber",
							"value": "1"
						}
					]
				}
			},
			"response": []
		},
		{
			"name": "Search SubCategory",
			"request": {
				"auth": {
					"type": "noauth"
				},
				"method": "GET",
				"header": [],
				"url": {
					"raw": "http://localhost:8080/api/search/sub-category?keyword=IOS&pageNumber=1",
					"protocol": "http",
					"host": [
						"localhost"
					],
					"port": "8080",
					"path": [
						"api",
						"search",
						"sub-category"
					],
					"query": [
						{
							"key": "keyword",
							"value": "IOS"
						},
						{
							"key": "pageNumber",
							"value": "1"
						}
					]
				}
			},
			"response": []
		},
		{
			"name": "Search Query",
			"request": {
				"auth": {
					"type": "noauth"
				},
				"method": "GET",
				"header": [],
				"url": {
					"raw": "http://localhost:8080/api/search?keyword=core&pageNumber=1",
					"protocol": "http",
					"host": [
						"localhost"
					],
					"port": "8080",
					"path": [
						"api",
						"search"
					],
					"query": [
						{
							"key": "keyword",
							"value": "core"
						},
						{
							"key": "pageNumber",
							"value": "1"
						}
					]
				}
			},
			"response": []
		}
	]
}